[{"id":"bitcoin","symbol":"btc","name":"Bitcoin","image":"https://assets.coingecko.com/coins/images/1/large/bitcoin.png?1696501400","current_price":41770,"market_cap":816620590614,"market_cap_rank":1,"fully_diluted_valuation":876240136397,"total_volume":18949175809,"high_24h":43036,"low_24h":41760,"price_change_24h":-1227.1099725395252,"price_change_percentage_24h":-2.85395,"market_cap_change_24h":-24699187224.750366,"market_cap_change_percentage_24h":-2.93577,"circulating_supply":19571156.0,"total_supply":21000000.0,"max_supply":21000000.0,"ath":69045,"ath_change_percentage":-39.57086,"ath_date":"2021-11-10T14:24:11.849Z","atl":67.81,"atl_change_percentage":61430.42127,"atl_date":"2013-07-06T00:00:00.000Z","roi":null,"last_updated":"2023-12-16T00:46:09.680Z"},{"id":"ethereum","symbol":"eth","name":"Ethereum","image":"https://assets.coingecko.com/coins/images/279/large/ethereum.png?1696501628","current_price":2221.55,"market_cap":265880767560,"market_cap_rank":2,"fully_diluted_valuation":265880767560,"total_volume":15396264966,"high_24h":2306.51,"low_24h":2212.6,"price_change_24h":-84.96173528048485,"price_change_percentage_24h":-3.68356,"market_cap_change_24h":-11119578906.589478,"market_cap_change_percentage_24h":-4.01428,"circulating_supply":120206615.736449,"total_supply":120206615.736449,"max_supply":null,"ath":4878.26,"ath_change_percentage":-54.64374,"ath_date":"2021-11-10T14:24:19.604Z","atl":0.432979,"atl_change_percentage":510917.18363,"atl_date":"2015-10-20T00:00:00.000Z","roi":{"times":70.04350792436914,"currency":"btc","percentage":7004.350792436913},"last_updated":"2023-12-16T00:45:45.759Z"},{"id":"tether","symbol":"usdt","name":"Tether","image":"https://assets.coingecko.com/coins/images/325/large/Tether.png?1696501661","current_price":1.0,"market_cap":90701393204,"market_cap_rank":3,"fully_diluted_valuation":90701393204,"total_volume":38769423965,"high_24h":1.002,"low_24h":0.99768,"price_change_24h":0.00015466,"price_change_percentage_24h":0.01546,"market_cap_change_24h":-70326354.0059967,"market_cap_change_percentage_24h":-0.07748,"circulating_supply":90817944690.4474,"total_supply":90817944690.4474,"max_supply":null,"ath":1.32,"ath_change_percentage":-24.51665,"ath_date":"2018-07-24T00:00:00.000Z","atl":0.572521,"atl_change_percentage":74.44192,"atl_date":"2015-03-02T00:00:00.000Z","roi":null,"last_updated":"2023-12-16T00:45:03.133Z"},{"id":"binancecoin","symbol":"bnb","name":"BNB","image":"https://assets.coingecko.com/coins/images/825/large/bnb-icon2_2x.png?1696501970","current_price":244.41,"market_cap":37508317304,"market_cap_rank":4,"fully_diluted_valuation":37508317304,"total_volume":676755173,"high_24h":252.96,"low_24h":243.76,"price_change_24h":-7.996295440042417,"price_change_percentage_24h":-3.16803,"market_cap_change_24h":-1294870525.240219,"market_cap_change_percentage_24h":-3.33702,"circulating_supply":153856150.0,"total_supply":153856150.0,"max_supply":200000000.0,"ath":686.31,"ath_change_percentage":-64.4775,"ath_date":"2021-05-10T07:24:17.097Z","atl":0.0398177,"atl_change_percentage":612173.61369,"atl_date":"2017-10-19T00:00:00.000Z","roi":null,"last_updated":"2023-12-16T00:46:11.096Z"},{"id":"ripple","symbol":"xrp","name":"XRP","image":"https://assets.coingecko.com/coins/images/44/large/xrp-symbol-white-128.png?1696501442","current_price":0.613397,"market_cap":33042939166,"market_cap_rank":5,"fully_diluted_valuation":61177036674,"total_volume":1286865534,"high_24h":0.640712,"low_24h":0.611624,"price_change_24h":-0.019010846262827008,"price_change_percentage_24h":-3.00611,"market_cap_change_24h":-1040058049.4656868,"market_cap_change_percentage_24h":-3.05155,"circulating_supply":54005597115.0,"total_supply":99988151135.0,"max_supply":100000000000.0,"ath":3.4,"ath_change_percentage":-82.00388,"ath_date":"2018-01-07T00:00:00.000Z","atl":0.00268621,"atl_change_percentage":22667.76699,"atl_date":"2014-05-22T00:00:00.000Z","roi":null,"last_updated":"2023-12-16T00:46:09.860Z"},{"id":"solana","symbol":"sol","name":"Solana","image":"https://assets.coingecko.com/coins/images/4128/large/solana.png?1696504756","current_price":72.13,"market_cap":30724260218,"market_cap_rank":6,"fully_diluted_valuation":40585875127,"total_volume":2757978073,"high_24h":79.21,"low_24h":71.78,"price_change_24h":-2.820016066608858,"price_change_percentage_24h":-3.76257,"market_cap_change_24h":-1229638804.8873672,"market_cap_change_percentage_24h":-3.84817,"circulating_supply":427619600.545123,"total_supply":564873347.202054,"max_supply":null,"ath":259.96,"ath_change_percentage":-72.36121,"ath_date":"2021-11-06T21:54:35.825Z","atl":0.500801,"atl_change_percentage":14246.92661,"atl_date":"2020-05-11T19:35:23.449Z","roi":null,"last_updated":"2023-12-16T00:46:09.059Z"},{"id":"usd-coin","symbol":"usdc","name":"USDC","image":"https://assets.coingecko.com/coins/images/6319/large/usdc.png?1696506694","current_price":1.0,"market_cap":24627308685,"market_cap_rank":7,"fully_diluted_valuation":24628639349,"total_volume":10429168448,"high_24h":1.003,"low_24h":0.997717,"price_change_24h":-0.000185579371837941,"price_change_percentage_24h":-0.01855,"market_cap_change_24h":147505385,"market_cap_change_percentage_24h":0.60256,"circulating_supply":24603393860.0307,"total_supply":24603451134.3032,"max_supply":null,"ath":1.17,"ath_change_percentage":-14.83471,"ath_date":"2019-05-08T00:40:28.300Z","atl":0.877647,"atl_change_percentage":13.79735,"atl_date":"2023-03-11T08:02:13.981Z","roi":null,"last_updated":"2023-12-16T00:46:10.021Z"},{"id":"cardano","symbol":"ada","name":"Cardano","image":"https://assets.coingecko.com/coins/images/975/large/cardano.png?1696502090","current_price":0.591592,"market_cap":20677325249,"market_cap_rank":8,"fully_diluted_valuation":26574522101,"total_volume":802120846,"high_24h":0.648927,"low_24h":0.590889,"price_change_24h":-0.05095562556927169,"price_change_percentage_24h":-7.93025,"market_cap_change_24h":-1808536873.5322456,"market_cap_change_percentage_24h":-8.043,"circulating_supply":35013974387.9469,"total_supply":45000000000.0,"max_supply":45000000000.0,"ath":3.09,"ath_change_percentage":-80.86939,"ath_date":"2021-09-02T06:00:10.474Z","atl":0.01925275,"atl_change_percentage":2967.3282,"atl_date":"2020-03-13T02:22:55.044Z","roi":null,"last_updated":"2023-12-16T00:46:06.172Z"},{"id":"staked-ether","symbol":"steth","name":"Lido Staked Ether","image":"https://assets.coingecko.com/coins/images/13442/large/steth_logo.png?1696513206","current_price":2216.05,"market_cap":20412264444,"market_cap_rank":9,"fully_diluted_valuation":20412264444,"total_volume":11539198,"high_24h":2304.23,"low_24h":2214.47,"price_change_24h":-88.18301718366638,"price_change_percentage_24h":-3.82701,"market_cap_change_24h":-815190703.9945946,"market_cap_change_percentage_24h":-3.84027,"circulating_supply":9219598.71096615,"total_supply":9219598.71096615,"max_supply":9219425.2103675,"ath":4829.57,"ath_change_percentage":-54.11302,"ath_date":"2021-11-10T14:40:47.256Z","atl":482.9,"atl_change_percentage":358.92764,"atl_date":"2020-12-22T04:08:21.854Z","roi":null,"last_updated":"2023-12-16T00:46:12.401Z"},{"id":"avalanche-2","symbol":"avax","name":"Avalanche","image":"https://assets.coingecko.com/coins/images/12559/large/Avalanche_Circle_RedWhite_Trans.png?1696512369","current_price":39.09,"market_cap":14316832712,"market_cap_rank":10,"fully_diluted_valuation":16977416672,"total_volume":1964516627,"high_24h":41.97,"low_24h":38.66,"price_change_24h":0.336742,"price_change_percentage_24h":0.86892,"market_cap_change_24h":159069343,"market_cap_change_percentage_24h":1.12355,"circulating_supply":366102852.551596,"total_supply":434134608.506403,"max_supply":720000000.0,"ath":144.96,"ath_change_percentage":-73.11292,"ath_date":"2021-11-21T14:18:56.538Z","atl":2.8,"atl_change_percentage":1291.46542,"atl_date":"2020-12-31T13:15:21.540Z","roi":null,"last_updated":"2023-12-16T00:46:09.845Z"},{"id":"dogecoin","symbol":"doge","name":"Dogecoin","image":"https://assets.coingecko.com/coins/images/5/large/dogecoin.png?1696501409","current_price":0.09222,"market_cap":13073082982,"market_cap_rank":11,"fully_diluted_valuation":13073044383,"total_volume":840135643,"high_24h":0.098491,"low_24h":0.091982,"price_change_24h":-0.006270247493118387,"price_change_percentage_24h":-6.36635,"market_cap_change_24h":-872099447.1621552,"market_cap_change_percentage_24h":-6.25377,"circulating_supply":142250206383.705,"total_supply":142250366383.705,"max_supply":null,"ath":0.731578,"ath_change_percentage":-87.42684,"ath_date":"2021-05-08T05:08:23.458Z","atl":8.69e-05,"atl_change_percentage":105744.09547,"atl_date":"2015-05-06T00:00:00.000Z","roi":null,"last_updated":"2023-12-16T00:45:55.497Z"},{"id":"polkadot","symbol":"dot","name":"Polkadot","image":"https://assets.coingecko.com/coins/images/12171/large/polkadot.png?1696512008","current_price":6.91,"market_cap":9024940030,"market_cap_rank":12,"fully_diluted_valuation":9583390990,"total_volume":400089793,"high_24h":7.56,"low_24h":6.9,"price_change_24h":-0.5892508900429769,"price_change_percentage_24h":-7.85671,"market_cap_change_24h":-760480965.3827381,"market_cap_change_percentage_24h":-7.77157,"circulating_supply":1308191984.9411,"total_supply":1389141117.80493,"max_supply":null,"ath":54.98,"ath_change_percentage":-87.4404,"ath_date":"2021-11-04T14:10:09.301Z","atl":2.7,"atl_change_percentage":155.99613,"atl_date":"2020-08-20T05:48:11.359Z","roi":null,"last_updated":"2023-12-16T00:45:56.344Z"},{"id":"tron","symbol":"trx","name":"TRON","image":"https://assets.coingecko.com/coins/images/1094/large/tron-logo.png?1696502193","current_price":0.101128,"market_cap":8951222377,"market_cap_rank":13,"fully_diluted_valuation":8951221866,"total_volume":332796315,"high_24h":0.106318,"low_24h":0.101109,"price_change_24h":-0.004871918578272503,"price_change_percentage_24h":-4.59615,"market_cap_change_24h":-411901516.4860916,"market_cap_change_percentage_24h":-4.39919,"circulating_supply":88418785978.1152,"total_supply":88418780933.7863,"max_supply":null,"ath":0.231673,"ath_change_percentage":-56.35617,"ath_date":"2018-01-05T00:00:00.000Z","atl":0.00180434,"atl_change_percentage":5503.75337,"atl_date":"2017-11-12T00:00:00.000Z","roi":{"times":52.22533001673516,"currency":"usd","percentage":5222.533001673516},"last_updated":"2023-12-16T00:46:01.858Z"},{"id":"chainlink","symbol":"link","name":"Chainlink","image":"https://assets.coingecko.com/coins/images/877/large/chainlink-new-logo.png?1696502009","current_price":14.2,"market_cap":7893439786,"market_cap_rank":14,"fully_diluted_valuation":14175164216,"total_volume":531874319,"high_24h":15.26,"low_24h":14.19,"price_change_24h":-1.065493308806019,"price_change_percentage_24h":-6.98123,"market_cap_change_24h":-599455288.0310946,"market_cap_change_percentage_24h":-7.05832,"circulating_supply":556849971.2305644,"total_supply":1000000000.0,"max_supply":1000000000.0,"ath":52.7,"ath_change_percentage":-73.10031,"ath_date":"2021-05-10T00:13:57.214Z","atl":0.148183,"atl_change_percentage":9466.01097,"atl_date":"2017-11-29T00:00:00.000Z","roi":null,"last_updated":"2023-12-16T00:46:01.075Z"},{"id":"matic-network","symbol":"matic","name":"Polygon","image":"https://assets.coingecko.com/coins/images/4713/large/polygon.png?1698233745","current_price":0.834258,"market_cap":7717752106,"market_cap_rank":15,"fully_diluted_valuation":8313906092,"total_volume":372917247,"high_24h":0.87894,"low_24h":0.832746,"price_change_24h":-0.0445168391502161,"price_change_percentage_24h":-5.06579,"market_cap_change_24h":-423512858.06951714,"market_cap_change_percentage_24h":-5.20205,"circulating_supply":9282943566.203985,"total_supply":10000000000.0,"max_supply":10000000000.0,"ath":2.92,"ath_change_percentage":-71.4901,"ath_date":"2021-12-27T02:08:34.307Z","atl":0.00314376,"atl_change_percentage":26346.79228,"atl_date":"2019-05-10T00:00:00.000Z","roi":{"times":316.20828085363877,"currency":"usd","percentage":31620.828085363875},"last_updated":"2023-12-16T00:46:00.572Z"},{"id":"wrapped-bitcoin","symbol":"wbtc","name":"Wrapped Bitcoin","image":"https://assets.coingecko.com/coins/images/7598/large/wrapped_bitcoin_wbtc.png?1696507857","current_price":41728,"market_cap":6455082239,"market_cap_rank":16,"fully_diluted_valuation":6455082239,"total_volume":123282319,"high_24h":42997,"low_24h":41649,"price_change_24h":-1079.7307647083653,"price_change_percentage_24h":-2.52227,"market_cap_change_24h":-169301938.3921795,"market_cap_change_percentage_24h":-2.55574,"circulating_supply":154744.26789025,"total_supply":154744.26789025,"max_supply":154744.26789025,"ath":70643,"ath_change_percentage":-41.02024,"ath_date":"2021-11-10T14:40:19.650Z","atl":3139.17,"atl_change_percentage":1227.27011,"atl_date":"2019-04-02T00:00:00.000Z","roi":null,"last_updated":"2023-12-16T00:46:03.564Z"},{"id":"shiba-inu","symbol":"shib","name":"Shiba Inu","image":"https://assets.coingecko.com/coins/images/11939/large/shiba.png?1696511800","current_price":9.55e-06,"market_cap":5622125842,"market_cap_rank":17,"fully_diluted_valuation":9539894225,"total_volume":195394895,"high_24h":1.004e-05,"low_24h":9.53e-06,"price_change_24h":-4.93053039908e-07,"price_change_percentage_24h":-4.91058,"market_cap_change_24h":-289630561.7457447,"market_cap_change_percentage_24h":-4.89923,"circulating_supply":589317524747437.2,"total_supply":999982392565752.0,"max_supply":null,"ath":8.616e-05,"ath_change_percentage":-88.92328,"ath_date":"2021-10-28T03:54:55.568Z","atl":5.6366e-11,"atl_change_percentage":16931214.70761,"atl_date":"2020-11-28T11:26:25.838Z","roi":null,"last_updated":"2023-12-16T00:46:03.064Z"},{"id":"litecoin","symbol":"ltc","name":"Litecoin","image":"https://assets.coingecko.com/coins/images/2/large/litecoin.png?1696501400","current_price":71.08,"market_cap":5237147309,"market_cap_rank":18,"fully_diluted_valuation":5946018786,"total_volume":291266260,"high_24h":72.65,"low_24h":70.76,"price_change_24h":-1.3720022231583187,"price_change_percentage_24h":-1.89365,"market_cap_change_24h":-115891263.16764069,"market_cap_change_percentage_24h":-2.16496,"circulating_supply":73985701.9834713,"total_supply":84000000.0,"max_supply":84000000.0,"ath":410.26,"ath_change_percentage":-82.74008,"ath_date":"2021-05-10T03:13:07.904Z","atl":1.15,"atl_change_percentage":6063.63964,"atl_date":"2015-01-14T00:00:00.000Z","roi":null,"last_updated":"2023-12-16T00:45:51.769Z"},{"id":"dai","symbol":"dai","name":"Dai","image":"https://assets.coingecko.com/coins/images/9956/large/Badge_Dai.png?1696509996","current_price":0.998145,"market_cap":5233241294,"market_cap_rank":19,"fully_diluted_valuation":5233241294,"total_volume":252778712,"high_24h":1.0,"low_24h":0.995099,"price_change_24h":-0.000104217918680649,"price_change_percentage_24h":-0.01044,"market_cap_change_24h":-26086033.473965645,"market_cap_change_percentage_24h":-0.496,"circulating_supply":5252524232.70551,"total_supply":5255249969.73022,"max_supply":null,"ath":1.22,"ath_change_percentage":-18.26205,"ath_date":"2020-03-13T03:02:50.373Z","atl":0.88196,"atl_change_percentage":12.9676,"atl_date":"2023-03-11T07:50:50.514Z","roi":null,"last_updated":"2023-12-16T00:45:03.824Z"},{"id":"uniswap","symbol":"uni","name":"Uniswap","image":"https://assets.coingecko.com/coins/images/12504/large/uni.jpg?1696512319","current_price":5.97,"market_cap":4496098861,"market_cap_rank":20,"fully_diluted_valuation":5964841718,"total_volume":108973504,"high_24h":6.29,"low_24h":5.95,"price_change_24h":-0.3115884295781175,"price_change_percentage_24h":-4.95764,"market_cap_change_24h":-235963664.05728912,"market_cap_change_percentage_24h":-4.98649,"circulating_supply":753766667.0,"total_supply":1000000000.0,"max_supply":1000000000.0,"ath":44.92,"ath_change_percentage":-86.71137,"ath_date":"2021-05-03T05:25:04.822Z","atl":1.03,"atl_change_percentage":479.41783,"atl_date":"2020-09-17T01:20:38.214Z","roi":null,"last_updated":"2023-12-16T00:46:11.185Z"},{"id":"bitcoin-cash","symbol":"bch","name":"Bitcoin Cash","image":"https://assets.coingecko.com/coins/images/780/large/bitcoin-cash-circle.png?1696501932","current_price":226.64,"market_cap":4429269547,"market_cap_rank":21,"fully_diluted_valuation":4748936606,"total_volume":127806217,"high_24h":236.79,"low_24h":226.18,"price_change_24h":-9.656255632444783,"price_change_percentage_24h":-4.08654,"market_cap_change_24h":-188820969.14126396,"market_cap_change_percentage_24h":-4.08872,"circulating_supply":19586418.6466508,"total_supply":21000000.0,"max_supply":21000000.0,"ath":3785.82,"ath_change_percentage":-94.02548,"ath_date":"2017-12-20T00:00:00.000Z","atl":76.93,"atl_change_percentage":193.99502,"atl_date":"2018-12-16T00:00:00.000Z","roi":null,"last_updated":"2023-12-16T00:45:49.834Z"},{"id":"okb","symbol":"okb","name":"OKB","image":"https://assets.coingecko.com/coins/images/4463/large/WeChat_Image_20220118095654.png?1696505053","current_price":57.29,"market_cap":3437959842,"market_cap_rank":22,"fully_diluted_valuation":13520217443,"total_volume":12705034,"high_24h":59.15,"low_24h":57.24,"price_change_24h":-1.8669365949812473,"price_change_percentage_24h":-3.15607,"market_cap_change_24h":-111119825.23792887,"market_cap_change_percentage_24h":-3.13095,"circulating_supply":60000000.0,"total_supply":235957685.3,"max_supply":300000000.0,"ath":64.92,"ath_change_percentage":-11.88985,"ath_date":"2023-11-14T16:15:10.918Z","atl":0.580608,"atl_change_percentage":9752.21369,"atl_date":"2019-01-14T00:00:00.000Z","roi":null,"last_updated":"2023-12-16T00:45:49.621Z"},{"id":"leo-token","symbol":"leo","name":"LEO Token","image":"https://assets.coingecko.com/coins/images/8418/large/leo-token.png?1696508607","current_price":3.71,"market_cap":3437168082,"market_cap_rank":23,"fully_diluted_valuation":3648366247,"total_volume":1339639,"high_24h":3.72,"low_24h":3.65,"price_change_24h":0.056364,"price_change_percentage_24h":1.54365,"market_cap_change_24h":48516687,"market_cap_change_percentage_24h":1.43174,"circulating_supply":928205543.9,"total_supply":985239504.0,"max_supply":null,"ath":8.14,"ath_change_percentage":-54.44208,"ath_date":"2022-02-08T17:40:10.285Z","atl":0.799859,"atl_change_percentage":363.36829,"atl_date":"2019-12-24T15:14:35.376Z","roi":null,"last_updated":"2023-12-16T00:45:48.349Z"},{"id":"stellar","symbol":"xlm","name":"Stellar","image":"https://assets.coingecko.com/coins/images/100/large/Stellar_symbol_black_RGB.png?1696501482","current_price":0.121881,"market_cap":3430130557,"market_cap_rank":24,"fully_diluted_valuation":6084123535,"total_volume":74147252,"high_24h":0.127942,"low_24h":0.121637,"price_change_24h":-0.005611364603357386,"price_change_percentage_24h":-4.40132,"market_cap_change_24h":-152781085.26004314,"market_cap_change_percentage_24h":-4.26416,"circulating_supply":28190199744.361,"total_supply":50001787069.7626,"max_supply":50001787069.7626,"ath":0.875563,"ath_change_percentage":-86.10759,"ath_date":"2018-01-03T00:00:00.000Z","atl":0.00047612,"atl_change_percentage":25447.32718,"atl_date":"2015-03-05T00:00:00.000Z","roi":null,"last_updated":"2023-12-16T00:46:13.093Z"},{"id":"internet-computer","symbol":"icp","name":"Internet Computer","image":"https://assets.coingecko.com/coins/images/14495/large/Internet_Computer_logo.png?1696514180","current_price":7.13,"market_cap":3212847102,"market_cap_rank":25,"fully_diluted_valuation":3640337123,"total_volume":207065965,"high_24h":7.56,"low_24h":6.22,"price_change_24h":0.896362,"price_change_percentage_24h":14.37651,"market_cap_change_24h":398703414,"market_cap_change_percentage_24h":14.16784,"circulating_supply":451176882.446982,"total_supply":511208954.864058,"max_supply":null,"ath":700.65,"ath_change_percentage":-98.98075,"ath_date":"2021-05-10T16:05:53.653Z","atl":2.87,"atl_change_percentage":149.25923,"atl_date":"2023-09-22T00:29:57.369Z","roi":null,"last_updated":"2023-12-16T00:46:12.453Z"},{"id":"cosmos","symbol":"atom","name":"Cosmos Hub","image":"https://assets.coingecko.com/coins/images/1481/large/cosmos_hub.png?1696502525","current_price":10.81,"market_cap":3156928534,"market_cap_rank":26,"fully_diluted_valuation":null,"total_volume":283125267,"high_24h":11.47,"low_24h":10.79,"price_change_24h":-0.6636741471847678,"price_change_percentage_24h":-5.78602,"market_cap_change_24h":-180834302.61652756,"market_cap_change_percentage_24h":-5.41783,"circulating_supply":292586163.827428,"total_supply":null,"max_supply":null,"ath":44.45,"ath_change_percentage":-75.72343,"ath_date":"2022-01-17T00:34:41.497Z","atl":1.16,"atl_change_percentage":830.16464,"atl_date":"2020-03-13T02:27:44.591Z","roi":{"times":107.0662794426163,"currency":"usd","percentage":10706.62794426163},"last_updated":"2023-12-16T00:46:12.951Z"},{"id":"monero","symbol":"xmr","name":"Monero","image":"https://assets.coingecko.com/coins/images/69/large/monero_logo.png?1696501460","current_price":167.83,"market_cap":3038352057,"market_cap_rank":27,"fully_diluted_valuation":null,"total_volume":89387091,"high_24h":172.07,"low_24h":167.44,"price_change_24h":-0.5398123773195493,"price_change_percentage_24h":-0.32062,"market_cap_change_24h":-16077551.13013935,"market_cap_change_percentage_24h":-0.52637,"circulating_supply":18147820.3764146,"total_supply":null,"max_supply":null,"ath":542.33,"ath_change_percentage":-69.1194,"ath_date":"2018-01-09T00:00:00.000Z","atl":0.216177,"atl_change_percentage":77370.6004,"atl_date":"2015-01-14T00:00:00.000Z","roi":null,"last_updated":"2023-12-16T00:46:08.551Z"},{"id":"ethereum-classic","symbol":"etc","name":"Ethereum Classic","image":"https://assets.coingecko.com/coins/images/453/large/ethereum-classic-logo.png?1696501717","current_price":19.85,"market_cap":2824391406,"market_cap_rank":28,"fully_diluted_valuation":4155659639,"total_volume":106716115,"high_24h":20.79,"low_24h":19.75,"price_change_24h":-0.9433444284426322,"price_change_percentage_24h":-4.53748,"market_cap_change_24h":-143297400.20421028,"market_cap_change_percentage_24h":-4.82859,"circulating_supply":143202119.751449,"total_supply":210700000.0,"max_supply":210700000.0,"ath":167.09,"ath_change_percentage":-88.18029,"ath_date":"2021-05-06T18:34:22.133Z","atl":0.615038,"atl_change_percentage":3111.02301,"atl_date":"2016-07-25T00:00:00.000Z","roi":{"times":43.10382222694182,"currency":"usd","percentage":4310.382222694182},"last_updated":"2023-12-16T00:46:10.159Z"},{"id":"immutable-x","symbol":"imx","name":"Immutable","image":"https://assets.coingecko.com/coins/images/17233/large/immutableX-symbol-BLK-RGB.png?1696516787","current_price":2.16,"market_cap":2759770297,"market_cap_rank":29,"fully_diluted_valuation":4284711429,"total_volume":185656037,"high_24h":2.29,"low_24h":2.07,"price_change_24h":-0.008283733241333469,"price_change_percentage_24h":-0.38171,"market_cap_change_24h":-19286778.706920147,"market_cap_change_percentage_24h":-0.694,"circulating_supply":1288194242.490024,"total_supply":2000000000.0,"max_supply":2000000000.0,"ath":9.52,"ath_change_percentage":-77.42344,"ath_date":"2021-11-26T01:03:01.536Z","atl":0.378055,"atl_change_percentage":468.50853,"atl_date":"2022-12-31T07:36:37.649Z","roi":null,"last_updated":"2023-12-16T00:46:01.168Z"},{"id":"hedera-hashgraph","symbol":"hbar","name":"Hedera","image":"https://assets.coingecko.com/coins/images/3688/large/hbar.png?1696504364","current_price":0.080023,"market_cap":2673843997,"market_cap_rank":30,"fully_diluted_valuation":3980547266,"total_volume":115104062,"high_24h":0.088039,"low_24h":0.079764,"price_change_24h":-0.004578566713551155,"price_change_percentage_24h":-5.4119,"market_cap_change_24h":-148513197.7767892,"market_cap_change_percentage_24h":-5.26203,"circulating_supply":33586386724.2941,"total_supply":50000000000.0,"max_supply":50000000000.0,"ath":0.569229,"ath_change_percentage":-86.01366,"ath_date":"2021-09-15T10:40:28.318Z","atl":0.00986111,"atl_change_percentage":707.3562,"atl_date":"2020-01-02T17:30:24.852Z","roi":null,"last_updated":"2023-12-16T00:46:07.536Z"},{"id":"crypto-com-chain","symbol":"cro","name":"Cronos","image":"https://assets.coingecko.com/coins/images/7310/large/cro_token_logo.png?1696507599","current_price":0.097919,"market_cap":2578037958,"market_cap_rank":31,"fully_diluted_valuation":2926713422,"total_volume":16402408,"high_24h":0.101532,"low_24h":0.097549,"price_change_24h":-0.003373450552957375,"price_change_percentage_24h":-3.3304,"market_cap_change_24h":-93813970.67608786,"market_cap_change_percentage_24h":-3.5112,"circulating_supply":26425935022.902,"total_supply":30000000000.0,"max_supply":null,"ath":0.965407,"ath_change_percentage":-89.89109,"ath_date":"2021-11-24T15:53:54.855Z","atl":0.0121196,"atl_change_percentage":705.24277,"atl_date":"2019-02-08T00:00:00.000Z","roi":null,"last_updated":"2023-12-16T00:46:13.519Z"},{"id":"kaspa","symbol":"kas","name":"Kaspa","image":"https://assets.coingecko.com/coins/images/25751/large/kaspa-icon-exchanges.png?1696524837","current_price":0.117164,"market_cap":2560515744,"market_cap_rank":32,"fully_diluted_valuation":2560467311,"total_volume":36102493,"high_24h":0.128885,"low_24h":0.116889,"price_change_24h":-0.011416078856113983,"price_change_percentage_24h":-8.87855,"market_cap_change_24h":-250320912.05762768,"market_cap_change_percentage_24h":-8.90557,"circulating_supply":21936935050.9183,"total_supply":21937061767.2655,"max_supply":28704026601.0,"ath":0.152699,"ath_change_percentage":-23.10693,"ath_date":"2023-11-19T21:34:58.238Z","atl":0.00017105,"atl_change_percentage":68543.99484,"atl_date":"2022-05-26T14:42:59.316Z","roi":null,"last_updated":"2023-12-16T00:46:12.288Z"},{"id":"aptos","symbol":"apt","name":"Aptos","image":"https://assets.coingecko.com/coins/images/26455/large/aptos_round.png?1696525528","current_price":8.21,"market_cap":2489208966,"market_cap_rank":33,"fully_diluted_valuation":8742747961,"total_volume":167063925,"high_24h":8.38,"low_24h":8.1,"price_change_24h":-0.16932792120896423,"price_change_percentage_24h":-2.02123,"market_cap_change_24h":-58075463.748560905,"market_cap_change_percentage_24h":-2.2799,"circulating_supply":304817012.152499,"total_supply":1070596461.49117,"max_supply":null,"ath":19.92,"ath_change_percentage":-58.54737,"ath_date":"2023-01-26T14:25:17.390Z","atl":3.08,"atl_change_percentage":168.11938,"atl_date":"2022-12-29T21:35:14.796Z","roi":null,"last_updated":"2023-12-16T00:45:59.852Z"},{"id":"injective-protocol","symbol":"inj","name":"Injective","image":"https://assets.coingecko.com/coins/images/12882/large/Secondary_Symbol.png?1696512670","current_price":29.72,"market_cap":2479310455,"market_cap_rank":34,"fully_diluted_valuation":2942607684,"total_volume":381033908,"high_24h":34.27,"low_24h":29.45,"price_change_24h":-1.2071644832029236,"price_change_percentage_24h":-3.90308,"market_cap_change_24h":-111091065.45925188,"market_cap_change_percentage_24h":-4.28857,"circulating_supply":84255555.66,"total_supply":100000000.0,"max_supply":100000000.0,"ath":34.27,"ath_change_percentage":-13.3644,"ath_date":"2023-12-15T16:55:08.213Z","atl":0.657401,"atl_change_percentage":4416.47842,"atl_date":"2020-11-03T16:19:30.576Z","roi":null,"last_updated":"2023-12-16T00:46:02.309Z"},{"id":"true-usd","symbol":"tusd","name":"TrueUSD","image":"https://assets.coingecko.com/coins/images/3449/large/tusd.png?1696504140","current_price":0.996446,"market_cap":2433647231,"market_cap_rank":35,"fully_diluted_valuation":2433647231,"total_volume":121251097,"high_24h":1.002,"low_24h":0.993079,"price_change_24h":-0.001902589986317316,"price_change_percentage_24h":-0.19057,"market_cap_change_24h":-24506333.051750183,"market_cap_change_percentage_24h":-0.99694,"circulating_supply":2442896872.14,"total_supply":2442896872.14,"max_supply":null,"ath":1.62,"ath_change_percentage":-38.54949,"ath_date":"2018-08-26T20:41:09.375Z","atl":0.88355,"atl_change_percentage":12.56685,"atl_date":"2020-03-12T10:47:51.380Z","roi":null,"last_updated":"2023-12-16T00:46:03.959Z"},{"id":"filecoin","symbol":"fil","name":"Filecoin","image":"https://assets.coingecko.com/coins/images/12817/large/filecoin.png?1696512609","current_price":4.75,"market_cap":2270968837,"market_cap_rank":36,"fully_diluted_valuation":9254464186,"total_volume":256040046,"high_24h":4.97,"low_24h":4.68,"price_change_24h":-0.08071503270367852,"price_change_percentage_24h":-1.67084,"market_cap_change_24h":-46501317.223403454,"market_cap_change_percentage_24h":-2.00656,"circulating_supply":481218004.0,"total_supply":1961019715.0,"max_supply":1961019769.0,"ath":236.84,"ath_change_percentage":-97.99716,"ath_date":"2021-04-01T13:29:41.564Z","atl":2.64,"atl_change_percentage":79.61359,"atl_date":"2022-12-16T22:45:28.552Z","roi":null,"last_updated":"2023-12-16T00:46:00.979Z"},{"id":"near","symbol":"near","name":"NEAR Protocol","image":"https://assets.coingecko.com/coins/images/10365/large/near.jpg?1696510367","current_price":2.18,"market_cap":2177972474,"market_cap_rank":37,"fully_diluted_valuation":2167856235,"total_volume":175974116,"high_24h":2.32,"low_24h":2.17,"price_change_24h":-0.10910420616125238,"price_change_percentage_24h":-4.76,"market_cap_change_24h":-123474378.65591002,"market_cap_change_percentage_24h":-5.36508,"circulating_supply":1004666471.68283,"total_supply":1000000000.0,"max_supply":null,"ath":20.44,"ath_change_percentage":-89.3546,"ath_date":"2022-01-16T22:09:45.873Z","atl":0.526762,"atl_change_percentage":313.03642,"atl_date":"2020-11-04T16:09:15.137Z","roi":null,"last_updated":"2023-12-16T00:46:06.015Z"},{"id":"vechain","symbol":"vet","name":"VeChain","image":"https://assets.coingecko.com/coins/images/1167/large/VET_Token_Icon.png?1696502256","current_price":0.02877091,"market_cap":2086860515,"market_cap_rank":38,"fully_diluted_valuation":2467716147,"total_volume":51045143,"high_24h":0.03037336,"low_24h":0.02873161,"price_change_24h":-0.001602449239591276,"price_change_percentage_24h":-5.27584,"market_cap_change_24h":-120726711.43796587,"market_cap_change_percentage_24h":-5.46872,"circulating_supply":72714516834.0,"total_supply":85985041177.0,"max_supply":86712634466.0,"ath":0.280991,"ath_change_percentage":-89.79973,"ath_date":"2021-04-19T01:08:21.675Z","atl":0.00191713,"atl_change_percentage":1395.03676,"atl_date":"2020-03-13T02:29:59.652Z","roi":{"times":3.5344310157751857,"currency":"eth","percentage":353.4431015775186},"last_updated":"2023-12-16T00:46:04.287Z"},{"id":"bittensor","symbol":"tao","name":"Bittensor","image":"https://assets.coingecko.com/coins/images/28452/large/ARUsPeNQ_400x400.jpeg?1696527447","current_price":349.02,"market_cap":2050587314,"market_cap_rank":39,"fully_diluted_valuation":2050587314,"total_volume":8618150,"high_24h":388.58,"low_24h":347.9,"price_change_24h":-26.41811358521386,"price_change_percentage_24h":-7.03652,"market_cap_change_24h":-151978208.51388574,"market_cap_change_percentage_24h":-6.90005,"circulating_supply":5849450.0,"total_supply":5849772.0,"max_supply":21000000.0,"ath":394.0,"ath_change_percentage":-10.03998,"ath_date":"2023-12-14T20:03:59.063Z","atl":30.83,"atl_change_percentage":1049.67859,"atl_date":"2023-05-14T08:57:53.732Z","roi":null,"last_updated":"2023-12-16T00:45:59.595Z"},{"id":"optimism","symbol":"op","name":"Optimism","image":"https://assets.coingecko.com/coins/images/25244/large/Optimism.png?1696524385","current_price":2.12,"market_cap":1914557411,"market_cap_rank":40,"fully_diluted_valuation":9023380943,"total_volume":198800949,"high_24h":2.28,"low_24h":2.09,"price_change_24h":-0.16146837395504843,"price_change_percentage_24h":-7.08322,"market_cap_change_24h":-159390649.7723391,"market_cap_change_percentage_24h":-7.68537,"circulating_supply":911294948.0,"total_supply":4294967296.0,"max_supply":4294967296.0,"ath":3.22,"ath_change_percentage":-34.26582,"ath_date":"2023-02-24T20:20:00.509Z","atl":0.402159,"atl_change_percentage":426.84024,"atl_date":"2022-06-18T20:54:52.178Z","roi":null,"last_updated":"2023-12-16T00:46:07.409Z"},{"id":"lido-dao","symbol":"ldo","name":"Lido DAO","image":"https://assets.coingecko.com/coins/images/13573/large/Lido_DAO.png?1696513326","current_price":2.14,"market_cap":1890468773,"market_cap_rank":41,"fully_diluted_valuation":2125157508,"total_volume":60940661,"high_24h":2.34,"low_24h":2.13,"price_change_24h":-0.1981577176991589,"price_change_percentage_24h":-8.48597,"market_cap_change_24h":-184617656.29346323,"market_cap_change_percentage_24h":-8.89687,"circulating_supply":889566427.803038,"total_supply":1000000000.0,"max_supply":1000000000.0,"ath":7.3,"ath_change_percentage":-70.7803,"ath_date":"2021-08-20T08:35:20.158Z","atl":0.40615,"atl_change_percentage":425.39173,"atl_date":"2022-06-18T20:55:12.035Z","roi":null,"last_updated":"2023-12-16T00:45:49.562Z"},{"id":"celestia","symbol":"tia","name":"Celestia","image":"https://assets.coingecko.com/coins/images/31967/large/tia.jpg?1696530772","current_price":12.96,"market_cap":1890396451,"market_cap_rank":42,"fully_diluted_valuation":13022356185,"total_volume":287362575,"high_24h":14.39,"low_24h":12.93,"price_change_24h":-0.8477091720670469,"price_change_percentage_24h":-6.13805,"market_cap_change_24h":-123997008.09949875,"market_cap_change_percentage_24h":-6.15555,"circulating_supply":145865445.558202,"total_supply":1004821917.8082,"max_supply":null,"ath":14.65,"ath_change_percentage":-10.71459,"ath_date":"2023-12-14T17:49:56.538Z","atl":2.08,"atl_change_percentage":527.72149,"atl_date":"2023-10-31T15:14:31.951Z","roi":null,"last_updated":"2023-12-16T00:46:09.897Z"},{"id":"mantle","symbol":"mnt","name":"Mantle","image":"https://assets.coingecko.com/coins/images/30980/large/token-logo.png?1696529819","current_price":0.578709,"market_cap":1807932054,"market_cap_rank":43,"fully_diluted_valuation":3591591581,"total_volume":26650763,"high_24h":0.600225,"low_24h":0.57823,"price_change_24h":-0.020528450538007448,"price_change_percentage_24h":-3.42576,"market_cap_change_24h":-67700075.87269044,"market_cap_change_percentage_24h":-3.60945,"circulating_supply":3130673946.01314,"total_supply":6219316794.99,"max_supply":6219316794.99,"ath":0.655497,"ath_change_percentage":-11.51085,"ath_date":"2023-12-08T03:49:59.990Z","atl":0.307978,"atl_change_percentage":88.33973,"atl_date":"2023-10-18T02:50:46.942Z","roi":null,"last_updated":"2023-12-16T00:45:58.446Z"},{"id":"thorchain","symbol":"rune","name":"THORChain","image":"https://assets.coingecko.com/coins/images/6595/large/Rune200x200.png?1696506946","current_price":5.64,"market_cap":1693631063,"market_cap_rank":44,"fully_diluted_valuation":2816142174,"total_volume":430619973,"high_24h":6.04,"low_24h":5.64,"price_change_24h":-0.2688239773706389,"price_change_percentage_24h":-4.55302,"market_cap_change_24h":-81080457.38654923,"market_cap_change_percentage_24h":-4.56866,"circulating_supply":300700561.0,"total_supply":500000000.0,"max_supply":500000000.0,"ath":20.87,"ath_change_percentage":-72.93039,"ath_date":"2021-05-19T00:30:09.436Z","atl":0.00851264,"atl_change_percentage":66257.4464,"atl_date":"2019-09-28T00:00:00.000Z","roi":{"times":147.30214788963048,"currency":"usd","percentage":14730.214788963047},"last_updated":"2023-12-16T00:46:00.427Z"},{"id":"first-digital-usd","symbol":"fdusd","name":"First Digital USD","image":"https://assets.coingecko.com/coins/images/31079/large/firstfigital.jpeg?1696529912","current_price":0.997857,"market_cap":1650261487,"market_cap_rank":45,"fully_diluted_valuation":1650261487,"total_volume":2472184201,"high_24h":1.004,"low_24h":0.993881,"price_change_24h":-0.003186586836334105,"price_change_percentage_24h":-0.31833,"market_cap_change_24h":255581351,"market_cap_change_percentage_24h":18.32545,"circulating_supply":1656786753.71,"total_supply":1656786753.71,"max_supply":null,"ath":1.041,"ath_change_percentage":-3.96163,"ath_date":"2023-10-23T22:55:15.103Z","atl":0.942129,"atl_change_percentage":6.15218,"atl_date":"2023-08-17T21:55:41.478Z","roi":null,"last_updated":"2023-12-16T00:46:10.656Z"},{"id":"render-token","symbol":"rndr","name":"Render","image":"https://assets.coingecko.com/coins/images/11636/large/rndr.png?1696511529","current_price":4.38,"market_cap":1636843785,"market_cap_rank":46,"fully_diluted_valuation":2321878084,"total_volume":147862418,"high_24h":4.72,"low_24h":4.35,"price_change_24h":-0.3000778307237466,"price_change_percentage_24h":-6.40994,"market_cap_change_24h":-104513247.10977483,"market_cap_change_percentage_24h":-6.00183,"circulating_supply":374355803.823796,"total_supply":531027178.103796,"max_supply":531027178.103796,"ath":8.78,"ath_change_percentage":-50.13564,"ath_date":"2021-11-21T10:03:19.097Z","atl":0.03665669,"atl_change_percentage":11847.58971,"atl_date":"2020-06-16T13:22:25.900Z","roi":null,"last_updated":"2023-12-16T00:46:13.469Z"},{"id":"quant-network","symbol":"qnt","name":"Quant","image":"https://assets.coingecko.com/coins/images/3370/large/5ZOu7brX_400x400.jpg?1696504070","current_price":109.39,"market_cap":1586666694,"market_cap_rank":47,"fully_diluted_valuation":1594119577,"total_volume":19632120,"high_24h":115.08,"low_24h":109.12,"price_change_24h":-5.068028311863742,"price_change_percentage_24h":-4.42772,"market_cap_change_24h":-75011220.44227982,"market_cap_change_percentage_24h":-4.51419,"circulating_supply":14544176.164091088,"total_supply":14612493.0,"max_supply":14612493.0,"ath":427.42,"ath_change_percentage":-74.48959,"ath_date":"2021-09-11T09:15:00.668Z","atl":0.215773,"atl_change_percentage":50433.21493,"atl_date":"2018-08-23T00:00:00.000Z","roi":{"times":20.18168199567493,"currency":"eth","percentage":2018.1681995674928},"last_updated":"2023-12-16T00:46:09.897Z"},{"id":"aave","symbol":"aave","name":"Aave","image":"https://assets.coingecko.com/coins/images/12645/large/AAVE.png?1696512452","current_price":106.06,"market_cap":1554602746,"market_cap_rank":48,"fully_diluted_valuation":1695778696,"total_volume":381626424,"high_24h":117.39,"low_24h":104.22,"price_change_24h":0.922459,"price_change_percentage_24h":0.87737,"market_cap_change_24h":10203174,"market_cap_change_percentage_24h":0.66066,"circulating_supply":14667977.606423162,"total_supply":16000000.0,"max_supply":16000000.0,"ath":661.69,"ath_change_percentage":-83.97518,"ath_date":"2021-05-18T21:19:59.514Z","atl":26.02,"atl_change_percentage":307.46285,"atl_date":"2020-11-05T09:20:11.928Z","roi":null,"last_updated":"2023-12-16T00:45:53.680Z"},{"id":"algorand","symbol":"algo","name":"Algorand","image":"https://assets.coingecko.com/coins/images/4380/large/download.png?1696504978","current_price":0.194866,"market_cap":1553760828,"market_cap_rank":49,"fully_diluted_valuation":1553760835,"total_volume":90191711,"high_24h":0.212196,"low_24h":0.19409,"price_change_24h":-0.01732996548630517,"price_change_percentage_24h":-8.16698,"market_cap_change_24h":-147320776.8279376,"market_cap_change_percentage_24h":-8.66042,"circulating_supply":8006614014.77616,"total_supply":8006614009.34516,"max_supply":10000000000.0,"ath":3.56,"ath_change_percentage":-94.549,"ath_date":"2019-06-20T14:51:19.480Z","atl":0.087513,"atl_change_percentage":121.81565,"atl_date":"2023-09-11T19:42:08.247Z","roi":{"times":-0.9188059987117893,"currency":"usd","percentage":-91.88059987117892},"last_updated":"2023-12-16T00:46:11.184Z"},{"id":"the-graph","symbol":"grt","name":"The Graph","image":"https://assets.coingecko.com/coins/images/13397/large/Graph_Token.png?1696513159","current_price":0.162013,"market_cap":1507751626,"market_cap_rank":50,"fully_diluted_valuation":1744667079,"total_volume":65089709,"high_24h":0.174029,"low_24h":0.161134,"price_change_24h":-0.010746170912698723,"price_change_percentage_24h":-6.22032,"market_cap_change_24h":-100979845.75007439,"market_cap_change_percentage_24h":-6.27699,"circulating_supply":9323057248.23284,"total_supply":10788004319.0,"max_supply":10788004319.0,"ath":2.84,"ath_change_percentage":-94.30688,"ath_date":"2021-02-12T07:28:45.775Z","atl":0.052051,"atl_change_percentage":210.79203,"atl_date":"2022-11-22T10:05:03.503Z","roi":null,"last_updated":"2023-12-16T00:46:03.652Z"},{"id":"elrond-erd-2","symbol":"egld","name":"MultiversX","image":"https://assets.coingecko.com/coins/images/12335/large/egld-token-logo.png?1696512162","current_price":57.47,"market_cap":1504720535,"market_cap_rank":51,"fully_diluted_valuation":1505014952,"total_volume":33715956,"high_24h":60.43,"low_24h":57.18,"price_change_24h":-2.9573674382056154,"price_change_percentage_24h":-4.89427,"market_cap_change_24h":-83830392.93172288,"market_cap_change_percentage_24h":-5.27716,"circulating_supply":26331092.0,"total_supply":26336244.0,"max_supply":31415926.0,"ath":545.64,"ath_change_percentage":-89.48359,"ath_date":"2021-11-23T10:33:26.737Z","atl":6.51,"atl_change_percentage":781.89107,"atl_date":"2020-10-07T01:44:53.554Z","roi":null,"last_updated":"2023-12-16T00:46:06.843Z"},{"id":"blockstack","symbol":"stx","name":"Stacks","image":"https://assets.coingecko.com/coins/images/2069/large/Stacks_logo_full.png?1696503035","current_price":0.973895,"market_cap":1387837009,"market_cap_rank":52,"fully_diluted_valuation":1766828406,"total_volume":60060411,"high_24h":1.065,"low_24h":0.970662,"price_change_24h":-0.0891224880619237,"price_change_percentage_24h":-8.38392,"market_cap_change_24h":-131385898.31895947,"market_cap_change_percentage_24h":-8.64823,"circulating_supply":1428032101.27805,"total_supply":1818000000.0,"max_supply":1818000000.0,"ath":3.39,"ath_change_percentage":-71.3287,"ath_date":"2021-12-01T01:32:34.725Z","atl":0.04559639,"atl_change_percentage":2031.42479,"atl_date":"2020-03-13T02:29:26.415Z","roi":{"times":7.115791889150107,"currency":"usd","percentage":711.5791889150107},"last_updated":"2023-12-16T00:46:10.467Z"},{"id":"arbitrum","symbol":"arb","name":"Arbitrum","image":"https://assets.coingecko.com/coins/images/16547/large/photo_2023-03-29_21.47.00.jpeg?1696516109","current_price":1.089,"market_cap":1384225857,"market_cap_rank":53,"fully_diluted_valuation":10856673386,"total_volume":259260084,"high_24h":1.17,"low_24h":1.086,"price_change_24h":-0.08485395724785394,"price_change_percentage_24h":-7.23057,"market_cap_change_24h":-112114250.0010376,"market_cap_change_percentage_24h":-7.49256,"circulating_supply":1275000000.0,"total_supply":10000000000.0,"max_supply":10000000000.0,"ath":8.67,"ath_change_percentage":-87.45076,"ath_date":"2023-03-23T13:10:03.106Z","atl":0.744925,"atl_change_percentage":46.11235,"atl_date":"2023-09-11T19:40:49.196Z","roi":null,"last_updated":"2023-12-16T00:45:50.447Z"},{"id":"bonk","symbol":"bonk","name":"Bonk","image":"https://assets.coingecko.com/coins/images/28600/large/bonk.jpg?1696527587","current_price":2.246e-05,"market_cap":1374033482,"market_cap_rank":54,"fully_diluted_valuation":2115995599,"total_volume":1702078913,"high_24h":3.416e-05,"low_24h":2.183e-05,"price_change_24h":-2.99781930601e-07,"price_change_percentage_24h":-1.31724,"market_cap_change_24h":-6994414.565742493,"market_cap_change_percentage_24h":-0.50646,"circulating_supply":60837624528359.55,"total_supply":93689234980611.55,"max_supply":100000000000000.0,"ath":3.416e-05,"ath_change_percentage":-31.78932,"ath_date":"2023-12-15T07:35:13.369Z","atl":8.6142e-08,"atl_change_percentage":26951.6823,"atl_date":"2022-12-29T22:48:46.755Z","roi":null,"last_updated":"2023-12-16T00:46:11.802Z"},{"id":"rocket-pool-eth","symbol":"reth","name":"Rocket Pool ETH","image":"https://assets.coingecko.com/coins/images/20764/large/reth.png?1696520159","current_price":2428.23,"market_cap":1324400228,"market_cap_rank":55,"fully_diluted_valuation":1324400228,"total_volume":1158096,"high_24h":2521.37,"low_24h":2427.64,"price_change_24h":-93.13783996584107,"price_change_percentage_24h":-3.69394,"market_cap_change_24h":-44430547.57043266,"market_cap_change_percentage_24h":-3.24588,"circulating_supply":545359.121398789,"total_supply":545359.121398789,"max_supply":null,"ath":4814.31,"ath_change_percentage":-49.5145,"ath_date":"2021-12-01T08:03:50.749Z","atl":887.26,"atl_change_percentage":173.93538,"atl_date":"2022-06-18T20:55:45.957Z","roi":null,"last_updated":"2023-12-16T00:46:10.343Z"},{"id":"havven","symbol":"snx","name":"Synthetix Network","image":"https://assets.coingecko.com/coins/images/3406/large/SNX.png?1696504103","current_price":4.01,"market_cap":1304994517,"market_cap_rank":56,"fully_diluted_valuation":1306682282,"total_volume":74984769,"high_24h":4.31,"low_24h":4.0,"price_change_24h":-0.27885622316297276,"price_change_percentage_24h":-6.50768,"market_cap_change_24h":-98379429.70062375,"market_cap_change_percentage_24h":-7.01021,"circulating_supply":327769196.13952357,"total_supply":328193104.088774,"max_supply":328193104.088774,"ath":28.53,"ath_change_percentage":-86.04412,"ath_date":"2021-02-14T01:12:38.505Z","atl":0.0347864,"atl_change_percentage":11346.80797,"atl_date":"2019-01-06T00:00:00.000Z","roi":{"times":7.012358667232082,"currency":"usd","percentage":701.2358667232082},"last_updated":"2023-12-16T00:46:11.073Z"},{"id":"maker","symbol":"mkr","name":"Maker","image":"https://assets.coingecko.com/coins/images/1364/large/Mark_Maker.png?1696502423","current_price":1308.86,"market_cap":1196855212,"market_cap_rank":57,"fully_diluted_valuation":1273382077,"total_volume":66171224,"high_24h":1355.37,"low_24h":1303.24,"price_change_24h":-46.51189657472764,"price_change_percentage_24h":-3.43167,"market_cap_change_24h":-44068531.433941364,"market_cap_change_percentage_24h":-3.55127,"circulating_supply":918878.020631294,"total_supply":977631.036950888,"max_supply":1005577.0,"ath":6292.31,"ath_change_percentage":-79.28834,"ath_date":"2021-05-03T21:54:29.333Z","atl":168.36,"atl_change_percentage":674.09227,"atl_date":"2020-03-16T20:52:36.527Z","roi":null,"last_updated":"2023-12-16T00:45:48.331Z"},{"id":"wemix-token","symbol":"wemix","name":"WEMIX","image":"https://assets.coingecko.com/coins/images/12998/large/wemixcoin_color_200.png?1696512788","current_price":3.43,"market_cap":1194374983,"market_cap_rank":58,"fully_diluted_valuation":3262190167,"total_volume":8333614,"high_24h":3.7,"low_24h":3.43,"price_change_24h":-0.2686901186060746,"price_change_percentage_24h":-7.27009,"market_cap_change_24h":-90920833.055444,"market_cap_change_percentage_24h":-7.07392,"circulating_supply":347162023.59593,"total_supply":948201825.987257,"max_supply":null,"ath":24.71,"ath_change_percentage":-86.0808,"ath_date":"2021-11-21T17:33:44.178Z","atl":0.128398,"atl_change_percentage":2578.91905,"atl_date":"2021-06-22T12:52:49.089Z","roi":null,"last_updated":"2023-12-16T00:45:51.984Z"},{"id":"binance-usd","symbol":"busd","name":"BUSD","image":"https://assets.coingecko.com/coins/images/9576/large/BUSDLOGO.jpg?1696509654","current_price":0.977559,"market_cap":1176809619,"market_cap_rank":59,"fully_diluted_valuation":1176809619,"total_volume":5399723,"high_24h":1.005,"low_24h":0.976068,"price_change_24h":-0.021560672748035192,"price_change_percentage_24h":-2.15797,"market_cap_change_24h":-77969341.46339822,"market_cap_change_percentage_24h":-6.21379,"circulating_supply":1205663333.72,"total_supply":1205663333.72,"max_supply":null,"ath":1.15,"ath_change_percentage":-15.44071,"ath_date":"2020-03-13T02:35:42.953Z","atl":0.901127,"atl_change_percentage":8.30732,"atl_date":"2021-05-19T13:04:37.445Z","roi":null,"last_updated":"2023-12-16T00:45:59.496Z"},{"id":"fantom","symbol":"ftm","name":"Fantom","image":"https://assets.coingecko.com/coins/images/4001/large/Fantom_round.png?1696504642","current_price":0.414145,"market_cap":1155583221,"market_cap_rank":60,"fully_diluted_valuation":1308650000,"total_volume":199001153,"high_24h":0.453753,"low_24h":0.412381,"price_change_24h":-0.0225403343114578,"price_change_percentage_24h":-5.16168,"market_cap_change_24h":-67436489.00879288,"market_cap_change_percentage_24h":-5.51393,"circulating_supply":2803634835.52659,"total_supply":3175000000.0,"max_supply":3175000000.0,"ath":3.46,"ath_change_percentage":-88.08256,"ath_date":"2021-10-28T05:19:39.845Z","atl":0.00190227,"atl_change_percentage":21567.46093,"atl_date":"2020-03-13T02:25:38.280Z","roi":{"times":12.804842272878346,"currency":"usd","percentage":1280.4842272878348},"last_updated":"2023-12-16T00:45:55.654Z"},{"id":"bittorrent","symbol":"btt","name":"BitTorrent","image":"https://assets.coingecko.com/coins/images/22457/large/btt_logo.png?1696521780","current_price":1.16e-06,"market_cap":1100032433,"market_cap_rank":61,"fully_diluted_valuation":1144636592,"total_volume":92263530,"high_24h":1.27e-06,"low_24h":1.16e-06,"price_change_24h":-1.08766856269e-07,"price_change_percentage_24h":-8.58578,"market_cap_change_24h":-103727163.0056498,"market_cap_change_percentage_24h":-8.61693,"circulating_supply":951421714286000.0,"total_supply":990000000000000.0,"max_supply":990000000000000.0,"ath":3.43e-06,"ath_change_percentage":-66.22896,"ath_date":"2022-01-21T04:00:31.909Z","atl":3.65368e-07,"atl_change_percentage":217.15959,"atl_date":"2023-10-13T05:10:41.241Z","roi":null,"last_updated":"2023-12-16T00:45:57.308Z"},{"id":"flow","symbol":"flow","name":"Flow","image":"https://assets.coingecko.com/coins/images/13446/large/5f6294c0c7a8cda55cb1c936_Flow_Wordmark.png?1696513210","current_price":0.743464,"market_cap":1091336630,"market_cap_rank":62,"fully_diluted_valuation":1091336630,"total_volume":34135101,"high_24h":0.809145,"low_24h":0.73939,"price_change_24h":-0.062080673254665375,"price_change_percentage_24h":-7.70667,"market_cap_change_24h":-98170392.47652292,"market_cap_change_percentage_24h":-8.25303,"circulating_supply":1476732732.0,"total_supply":1476732731.73552,"max_supply":1476732731.73552,"ath":42.4,"ath_change_percentage":-98.24713,"ath_date":"2021-04-05T13:49:10.098Z","atl":0.391969,"atl_change_percentage":89.59876,"atl_date":"2023-09-11T19:41:06.528Z","roi":null,"last_updated":"2023-12-16T00:46:10.732Z"},{"id":"helium","symbol":"hnt","name":"Helium","image":"https://assets.coingecko.com/coins/images/4284/large/Helium_HNT.png?1696504894","current_price":7.55,"market_cap":1083965714,"market_cap_rank":63,"fully_diluted_valuation":1679401502,"total_volume":53375116,"high_24h":8.74,"low_24h":6.56,"price_change_24h":0.989213,"price_change_percentage_24h":15.07972,"market_cap_change_24h":146359423,"market_cap_change_percentage_24h":15.6099,"circulating_supply":143934820.830308,"total_supply":223000000.0,"max_supply":223000000.0,"ath":54.88,"ath_change_percentage":-86.27669,"ath_date":"2021-11-12T23:08:25.301Z","atl":0.113248,"atl_change_percentage":6549.98176,"atl_date":"2020-04-18T00:19:10.902Z","roi":null,"last_updated":"2023-12-16T00:45:58.861Z"},{"id":"ordinals","symbol":"ordi","name":"ORDI","image":"https://assets.coingecko.com/coins/images/30162/large/ordi.png?1696529082","current_price":49.78,"market_cap":1047984382,"market_cap_rank":64,"fully_diluted_valuation":1047984382,"total_volume":864611760,"high_24h":66.64,"low_24h":49.81,"price_change_24h":-16.868989441916185,"price_change_percentage_24h":-25.31192,"market_cap_change_24h":-335439011.3069596,"market_cap_change_percentage_24h":-24.24702,"circulating_supply":21000000.0,"total_supply":21000000.0,"max_supply":null,"ath":68.37,"ath_change_percentage":-24.5922,"ath_date":"2023-12-06T17:55:18.420Z","atl":2.86,"atl_change_percentage":1702.07174,"atl_date":"2023-09-11T15:22:32.140Z","roi":null,"last_updated":"2023-12-16T00:46:10.974Z"},{"id":"kucoin-shares","symbol":"kcs","name":"KuCoin","image":"https://assets.coingecko.com/coins/images/1047/large/sa9z79.png?1696502152","current_price":10.85,"market_cap":1045107118,"market_cap_rank":65,"fully_diluted_valuation":1558299050,"total_volume":650304,"high_24h":11.48,"low_24h":10.64,"price_change_24h":-0.6292733924194582,"price_change_percentage_24h":-5.48208,"market_cap_change_24h":-63638245.97221887,"market_cap_change_percentage_24h":-5.73966,"circulating_supply":96732986.3190288,"total_supply":144232986.318945,"max_supply":null,"ath":28.83,"ath_change_percentage":-62.55437,"ath_date":"2021-12-01T15:09:35.541Z","atl":0.342863,"atl_change_percentage":3048.64318,"atl_date":"2019-02-07T00:00:00.000Z","roi":null,"last_updated":"2023-12-16T00:45:50.091Z"},{"id":"theta-token","symbol":"theta","name":"Theta Network","image":"https://assets.coingecko.com/coins/images/2538/large/theta-token-logo.png?1696503349","current_price":1.036,"market_cap":1032735817,"market_cap_rank":66,"fully_diluted_valuation":1032735817,"total_volume":15373962,"high_24h":1.11,"low_24h":1.03,"price_change_24h":-0.07579940898435966,"price_change_percentage_24h":-6.81962,"market_cap_change_24h":-75957100.9464699,"market_cap_change_percentage_24h":-6.85105,"circulating_supply":1000000000.0,"total_supply":1000000000.0,"max_supply":1000000000.0,"ath":15.72,"ath_change_percentage":-93.45035,"ath_date":"2021-04-16T13:15:11.190Z","atl":0.04039979,"atl_change_percentage":2448.49396,"atl_date":"2020-03-13T02:24:16.483Z","roi":{"times":5.90460536822802,"currency":"usd","percentage":590.460536822802},"last_updated":"2023-12-16T00:46:07.832Z"},{"id":"the-sandbox","symbol":"sand","name":"The Sandbox","image":"https://assets.coingecko.com/coins/images/12129/large/sandbox_logo.jpg?1696511971","current_price":0.490718,"market_cap":1029835088,"market_cap_rank":67,"fully_diluted_valuation":1469980651,"total_volume":95922766,"high_24h":0.52789,"low_24h":0.488838,"price_change_24h":-0.03624150779361419,"price_change_percentage_24h":-6.87747,"market_cap_change_24h":-75808123.68856323,"market_cap_change_percentage_24h":-6.85647,"circulating_supply":2101731926.2233226,"total_supply":3000000000.0,"max_supply":3000000000.0,"ath":8.4,"ath_change_percentage":-94.16064,"ath_date":"2021-11-25T06:04:40.957Z","atl":0.02897764,"atl_change_percentage":1592.05999,"atl_date":"2020-11-04T15:59:14.441Z","roi":null,"last_updated":"2023-12-16T00:45:59.072Z"},{"id":"beam-2","symbol":"beam","name":"Beam","image":"https://assets.coingecko.com/coins/images/32417/large/chain-logo.png?1698114384","current_price":0.02043924,"market_cap":978718540,"market_cap_rank":68,"fully_diluted_valuation":1289763838,"total_volume":60080199,"high_24h":0.02496905,"low_24h":0.02041025,"price_change_24h":-0.003876808892417663,"price_change_percentage_24h":-15.94342,"market_cap_change_24h":-169635026.13910246,"market_cap_change_percentage_24h":-14.77202,"circulating_supply":47514525179.7597,"total_supply":62615056183.5095,"max_supply":62615056183.5095,"ath":0.02720031,"ath_change_percentage":-23.62426,"ath_date":"2023-12-14T05:24:58.029Z","atl":0.0043383,"atl_change_percentage":378.86112,"atl_date":"2023-10-29T08:20:14.064Z","roi":null,"last_updated":"2023-12-16T00:46:11.414Z"},{"id":"terra-luna","symbol":"lunc","name":"Terra Luna Classic","image":"https://assets.coingecko.com/coins/images/8284/large/01_LunaClassic_color.png?1696508486","current_price":0.00016461,"market_cap":958253355,"market_cap_rank":69,"fully_diluted_valuation":1121045941,"total_volume":145979438,"high_24h":0.00019136,"low_24h":0.000164,"price_change_24h":-1.9148102088678e-05,"price_change_percentage_24h":-10.42039,"market_cap_change_24h":-109820062.79936326,"market_cap_change_percentage_24h":-10.28207,"circulating_supply":5831216118181.63,"total_supply":6821850534721.5,"max_supply":null,"ath":119.18,"ath_change_percentage":-99.99986,"ath_date":"2022-04-05T12:24:58.854Z","atl":9.99967e-07,"atl_change_percentage":16305.06579,"atl_date":"2022-05-13T02:34:40.340Z","roi":null,"last_updated":"2023-12-16T00:45:59.349Z"},{"id":"bitcoin-cash-sv","symbol":"bsv","name":"Bitcoin SV","image":"https://assets.coingecko.com/coins/images/6799/large/BSV.png?1696507128","current_price":48.13,"market_cap":938962151,"market_cap_rank":70,"fully_diluted_valuation":1007060094,"total_volume":34567561,"high_24h":50.17,"low_24h":47.96,"price_change_24h":-1.6629848670296994,"price_change_percentage_24h":-3.33963,"market_cap_change_24h":-35877842.89603615,"market_cap_change_percentage_24h":-3.68038,"circulating_supply":19579968.75,"total_supply":21000000.0,"max_supply":21000000.0,"ath":489.75,"ath_change_percentage":-90.21508,"ath_date":"2021-04-16T17:09:04.630Z","atl":21.43,"atl_change_percentage":123.56939,"atl_date":"2023-06-10T04:32:12.266Z","roi":null,"last_updated":"2023-12-16T00:46:01.733Z"},{"id":"neo","symbol":"neo","name":"NEO","image":"https://assets.coingecko.com/coins/images/480/large/NEO_512_512.png?1696501735","current_price":13.32,"market_cap":936393042,"market_cap_rank":71,"fully_diluted_valuation":1327652122,"total_volume":83444003,"high_24h":13.7,"low_24h":12.74,"price_change_24h":0.341956,"price_change_percentage_24h":2.63478,"market_cap_change_24h":22895669,"market_cap_change_percentage_24h":2.50637,"circulating_supply":70530000.0,"total_supply":100000000.0,"max_supply":null,"ath":198.38,"ath_change_percentage":-93.29034,"ath_date":"2018-01-15T00:00:00.000Z","atl":0.078349,"atl_change_percentage":16888.92223,"atl_date":"2016-10-21T00:00:00.000Z","roi":{"times":369.0133526378061,"currency":"usd","percentage":36901.33526378061},"last_updated":"2023-12-16T00:46:05.014Z"},{"id":"axie-infinity","symbol":"axs","name":"Axie Infinity","image":"https://assets.coingecko.com/coins/images/13029/large/axie_infinity_logo.png?1696512817","current_price":6.97,"market_cap":929135100,"market_cap_rank":72,"fully_diluted_valuation":1871212966,"total_volume":54773357,"high_24h":7.37,"low_24h":6.94,"price_change_24h":-0.39552462934331256,"price_change_percentage_24h":-5.36868,"market_cap_change_24h":-51807279.26248813,"market_cap_change_percentage_24h":-5.28138,"circulating_supply":134066234.864285,"total_supply":270000000.0,"max_supply":270000000.0,"ath":164.9,"ath_change_percentage":-95.78318,"ath_date":"2021-11-06T19:29:29.482Z","atl":0.123718,"atl_change_percentage":5520.39151,"atl_date":"2020-11-06T08:05:43.662Z","roi":null,"last_updated":"2023-12-16T00:46:02.889Z"},{"id":"decentraland","symbol":"mana","name":"Decentraland","image":"https://assets.coingecko.com/coins/images/878/large/decentraland-mana.png?1696502010","current_price":0.481817,"market_cap":885562021,"market_cap_rank":73,"fully_diluted_valuation":1051558906,"total_volume":84518884,"high_24h":0.510166,"low_24h":0.479468,"price_change_24h":-0.02799380853915917,"price_change_percentage_24h":-5.49102,"market_cap_change_24h":-53489216.92855549,"market_cap_change_percentage_24h":-5.69609,"circulating_supply":1846968634.8787756,"total_supply":2193179327.32015,"max_supply":2193179327.32015,"ath":5.85,"ath_change_percentage":-91.79858,"ath_date":"2021-11-25T10:04:18.534Z","atl":0.00923681,"atl_change_percentage":5094.97897,"atl_date":"2017-10-31T00:00:00.000Z","roi":{"times":23.090829281395035,"currency":"usd","percentage":2309.0829281395036},"last_updated":"2023-12-16T00:46:03.147Z"},{"id":"gala","symbol":"gala","name":"GALA","image":"https://assets.coingecko.com/coins/images/12493/large/GALA-COINGECKO.png?1696512310","current_price":0.02946733,"market_cap":871022513,"market_cap_rank":74,"fully_diluted_valuation":871010639,"total_volume":113836789,"high_24h":0.03185983,"low_24h":0.02895187,"price_change_24h":-0.002392498993795324,"price_change_percentage_24h":-7.50945,"market_cap_change_24h":-74559561.20539796,"market_cap_change_percentage_24h":-7.88504,"circulating_supply":29759672504.4291,"total_supply":29759901537.9658,"max_supply":50000000000.0,"ath":0.824837,"ath_change_percentage":-96.47316,"ath_date":"2021-11-26T01:03:48.731Z","atl":0.00013475,"atl_change_percentage":21488.72221,"atl_date":"2020-12-28T08:46:48.367Z","roi":null,"last_updated":"2023-12-16T00:46:07.465Z"},{"id":"iota","symbol":"iota","name":"IOTA","image":"https://assets.coingecko.com/coins/images/692/large/IOTA_Swirl.png?1696501881","current_price":0.282657,"market_cap":859386290,"market_cap_rank":75,"fully_diluted_valuation":1293043237,"total_volume":19394086,"high_24h":0.311332,"low_24h":0.283248,"price_change_24h":-0.022471125633068138,"price_change_percentage_24h":-7.36448,"market_cap_change_24h":-81279368.27239501,"market_cap_change_percentage_24h":-8.64062,"circulating_supply":3057265852.0,"total_supply":4600000000.0,"max_supply":4600000000.0,"ath":5.25,"ath_change_percentage":-94.61215,"ath_date":"2017-12-19T00:00:00.000Z","atl":0.081637,"atl_change_percentage":246.4053,"atl_date":"2020-03-13T02:22:41.168Z","roi":{"times":4.045348357324388,"currency":"btc","percentage":404.53483573243875},"last_updated":"2023-12-16T00:45:57.682Z"},{"id":"osmosis","symbol":"osmo","name":"Osmosis","image":"https://assets.coingecko.com/coins/images/16724/large/osmo.png?1696516298","current_price":1.35,"market_cap":852330921,"market_cap_rank":76,"fully_diluted_valuation":1346421334,"total_volume":71191612,"high_24h":1.41,"low_24h":1.23,"price_change_24h":0.104356,"price_change_percentage_24h":8.38979,"market_cap_change_24h":66224069,"market_cap_change_percentage_24h":8.42431,"circulating_supply":633021220.0,"total_supply":999979298.0,"max_supply":1000000000.0,"ath":11.25,"ath_change_percentage":-88.01555,"ath_date":"2022-03-04T05:12:18.707Z","atl":0.224523,"atl_change_percentage":500.44608,"atl_date":"2023-10-19T17:45:36.695Z","roi":null,"last_updated":"2023-12-16T00:46:00.971Z"},{"id":"eos","symbol":"eos","name":"EOS","image":"https://assets.coingecko.com/coins/images/738/large/eos-eos-logo.png?1696501893","current_price":0.750952,"market_cap":845730402,"market_cap_rank":77,"fully_diluted_valuation":null,"total_volume":124816647,"high_24h":0.797956,"low_24h":0.747923,"price_change_24h":-0.03700353488090524,"price_change_percentage_24h":-4.69614,"market_cap_change_24h":-44524028.149449825,"market_cap_change_percentage_24h":-5.00127,"circulating_supply":1131686171.7322,"total_supply":null,"max_supply":null,"ath":22.71,"ath_change_percentage":-96.70683,"ath_date":"2018-04-29T07:50:33.540Z","atl":0.5024,"atl_change_percentage":48.86979,"atl_date":"2017-10-23T00:00:00.000Z","roi":{"times":-0.2414623110909698,"currency":"usd","percentage":-24.14623110909698},"last_updated":"2023-12-16T00:46:06.629Z"},{"id":"whitebit","symbol":"wbt","name":"WhiteBIT Coin","image":"https://assets.coingecko.com/coins/images/27045/large/wbt_token.png?1696526096","current_price":5.67,"market_cap":818018014,"market_cap_rank":78,"fully_diluted_valuation":2059563132,"total_volume":7920210,"high_24h":5.76,"low_24h":5.66,"price_change_24h":-0.0268102825159664,"price_change_percentage_24h":-0.47054,"market_cap_change_24h":-2623089.4608951807,"market_cap_change_percentage_24h":-0.31964,"circulating_supply":144118517.10815412,"total_supply":362854093.0,"max_supply":400000000.0,"ath":14.64,"ath_change_percentage":-61.22969,"ath_date":"2022-10-28T12:32:18.119Z","atl":3.06,"atl_change_percentage":85.44382,"atl_date":"2023-02-13T19:01:21.899Z","roi":null,"last_updated":"2023-12-16T00:46:10.117Z"},{"id":"kava","symbol":"kava","name":"Kava","image":"https://assets.coingecko.com/coins/images/9761/large/kava.png?1696509822","current_price":0.791949,"market_cap":812186583,"market_cap_rank":79,"fully_diluted_valuation":812100088,"total_volume":25775997,"high_24h":0.823865,"low_24h":0.792209,"price_change_24h":-0.009278912929273188,"price_change_percentage_24h":-1.15809,"market_cap_change_24h":-9725356.702799201,"market_cap_change_percentage_24h":-1.18326,"circulating_supply":1028888030.0,"total_supply":1028917841.0,"max_supply":null,"ath":9.12,"ath_change_percentage":-91.32453,"ath_date":"2021-08-30T11:10:02.948Z","atl":0.287137,"atl_change_percentage":175.55629,"atl_date":"2020-03-13T02:24:16.835Z","roi":null,"last_updated":"2023-12-16T00:46:03.255Z"},{"id":"tezos","symbol":"xtz","name":"Tezos","image":"https://assets.coingecko.com/coins/images/976/large/Tezos-logo.png?1696502091","current_price":0.906782,"market_cap":809959478,"market_cap_rank":80,"fully_diluted_valuation":891960492,"total_volume":26132813,"high_24h":0.969847,"low_24h":0.9045,"price_change_24h":-0.05653145778038404,"price_change_percentage_24h":-5.86844,"market_cap_change_24h":-52684503.54316342,"market_cap_change_percentage_24h":-6.10733,"circulating_supply":894077208.21762,"total_supply":984594375.475286,"max_supply":null,"ath":9.12,"ath_change_percentage":-90.08086,"ath_date":"2021-10-04T00:41:18.025Z","atl":0.350476,"atl_change_percentage":158.00215,"atl_date":"2018-12-07T00:00:00.000Z","roi":{"times":0.9293236744679677,"currency":"usd","percentage":92.93236744679676},"last_updated":"2023-12-16T00:46:02.634Z"},{"id":"klay-token","symbol":"klay","name":"Klaytn","image":"https://assets.coingecko.com/coins/images/9672/large/klaytn.png?1696509742","current_price":0.235235,"market_cap":767665908,"market_cap_rank":81,"fully_diluted_valuation":1373763783,"total_volume":22832880,"high_24h":0.253885,"low_24h":0.234155,"price_change_24h":-0.01765941472545199,"price_change_percentage_24h":-6.98292,"market_cap_change_24h":-61047270.69895625,"market_cap_change_percentage_24h":-7.36651,"circulating_supply":3277350839.09336,"total_supply":5864952138.60806,"max_supply":null,"ath":4.34,"ath_change_percentage":-94.59793,"ath_date":"2021-03-30T03:44:28.828Z","atl":0.06044,"atl_change_percentage":287.81038,"atl_date":"2020-04-29T08:19:34.574Z","roi":null,"last_updated":"2023-12-16T00:45:59.065Z"},{"id":"mina-protocol","symbol":"mina","name":"Mina Protocol","image":"https://assets.coingecko.com/coins/images/15628/large/JM4_vQ34_400x400.png?1696515261","current_price":0.739226,"market_cap":751790775,"market_cap_rank":82,"fully_diluted_valuation":815650078,"total_volume":16118697,"high_24h":0.791298,"low_24h":0.735067,"price_change_24h":-0.050729888345729335,"price_change_percentage_24h":-6.42186,"market_cap_change_24h":-50759127.666730285,"market_cap_change_percentage_24h":-6.32473,"circulating_supply":1018432354.84004,"total_supply":1104942412.84004,"max_supply":null,"ath":9.09,"ath_change_percentage":-91.86269,"ath_date":"2021-06-01T01:42:37.064Z","atl":0.351341,"atl_change_percentage":110.53865,"atl_date":"2023-10-11T04:00:22.740Z","roi":null,"last_updated":"2023-12-16T00:46:06.154Z"},{"id":"dydx","symbol":"ethdydx","name":"dYdX","image":"https://assets.coingecko.com/coins/images/17500/large/hjnIm9bV.jpg?1696517040","current_price":2.79,"market_cap":740652706,"market_cap_rank":83,"fully_diluted_valuation":2777562074,"total_volume":133435087,"high_24h":2.93,"low_24h":2.78,"price_change_24h":-0.1373043008698227,"price_change_percentage_24h":-4.69615,"market_cap_change_24h":-37448506.91860616,"market_cap_change_percentage_24h":-4.81281,"circulating_supply":266655680.79762536,"total_supply":1000000000.0,"max_supply":1000000000.0,"ath":27.86,"ath_change_percentage":-90.00294,"ath_date":"2021-09-30T01:23:43.570Z","atl":1.011,"atl_change_percentage":175.60053,"atl_date":"2022-06-18T20:55:50.603Z","roi":null,"last_updated":"2023-12-16T00:45:48.405Z"},{"id":"woo-network","symbol":"woo","name":"WOO Network","image":"https://assets.coingecko.com/coins/images/12921/large/WOO_Logos_2023_Profile_Pic_WOO.png?1696512709","current_price":0.406129,"market_cap":724918571,"market_cap_rank":84,"fully_diluted_valuation":908547002,"total_volume":153548993,"high_24h":0.453835,"low_24h":0.352088,"price_change_24h":0.01905131,"price_change_percentage_24h":4.92183,"market_cap_change_24h":34507640,"market_cap_change_percentage_24h":4.99813,"circulating_supply":1779636616.98445,"total_supply":2230434666.90186,"max_supply":2230434666.90186,"ath":1.78,"ath_change_percentage":-77.09372,"ath_date":"2021-11-15T13:44:18.437Z","atl":0.02211546,"atl_change_percentage":1741.88272,"atl_date":"2021-01-04T10:19:13.803Z","roi":null,"last_updated":"2023-12-16T00:46:12.375Z"},{"id":"bitget-token","symbol":"bgb","name":"Bitget Token","image":"https://assets.coingecko.com/coins/images/11610/large/icon_colour.png?1696511504","current_price":0.520016,"market_cap":724131132,"market_cap_rank":85,"fully_diluted_valuation":1034472308,"total_volume":19865582,"high_24h":0.540029,"low_24h":0.491137,"price_change_24h":0.02529329,"price_change_percentage_24h":5.11262,"market_cap_change_24h":27839025,"market_cap_change_percentage_24h":3.99818,"circulating_supply":1400001000.0,"total_supply":2000000000.0,"max_supply":2000000000.0,"ath":0.583922,"ath_change_percentage":-11.15773,"ath_date":"2023-11-13T23:30:28.560Z","atl":0.0142795,"atl_change_percentage":3532.96386,"atl_date":"2020-06-25T04:17:05.895Z","roi":null,"last_updated":"2023-12-16T00:45:57.413Z"},{"id":"usdd","symbol":"usdd","name":"USDD","image":"https://assets.coingecko.com/coins/images/25380/large/UUSD.jpg?1696524513","current_price":0.987874,"market_cap":717171226,"market_cap_rank":86,"fully_diluted_valuation":null,"total_volume":13236955,"high_24h":0.991002,"low_24h":0.97987,"price_change_24h":-0.002859078406630578,"price_change_percentage_24h":-0.28858,"market_cap_change_24h":-153039.22054505348,"market_cap_change_percentage_24h":-0.02133,"circulating_supply":725332033.742248,"total_supply":null,"max_supply":null,"ath":1.052,"ath_change_percentage":-6.09498,"ath_date":"2023-10-23T22:45:25.398Z","atl":0.928067,"atl_change_percentage":6.42669,"atl_date":"2022-06-19T16:15:11.558Z","roi":null,"last_updated":"2023-12-16T00:46:10.643Z"},{"id":"xdce-crowd-sale","symbol":"xdc","name":"XDC Network","image":"https://assets.coingecko.com/coins/images/2912/large/xdc-icon.png?1696503661","current_price":0.051361,"market_cap":714481918,"market_cap_rank":87,"fully_diluted_valuation":1949299521,"total_volume":17978378,"high_24h":0.051673,"low_24h":0.04854775,"price_change_24h":0.00227108,"price_change_percentage_24h":4.62634,"market_cap_change_24h":31770439,"market_cap_change_percentage_24h":4.65357,"circulating_supply":13884376866.15,"total_supply":37880327674.95,"max_supply":null,"ath":0.192754,"ath_change_percentage":-73.29374,"ath_date":"2021-08-21T04:39:48.324Z","atl":0.00039532,"atl_change_percentage":12921.77037,"atl_date":"2019-07-22T00:00:00.000Z","roi":{"times":2.0748563555337167,"currency":"eth","percentage":207.48563555337168},"last_updated":"2023-12-16T00:45:59.060Z"},{"id":"gatechain-token","symbol":"gt","name":"Gate","image":"https://assets.coingecko.com/coins/images/8183/large/gate.png?1696508395","current_price":5.19,"market_cap":706320092,"market_cap_rank":88,"fully_diluted_valuation":1555402299,"total_volume":4063229,"high_24h":5.49,"low_24h":4.78,"price_change_24h":0.397729,"price_change_percentage_24h":8.30213,"market_cap_change_24h":51330919,"market_cap_change_percentage_24h":7.83691,"circulating_supply":136232296.7235079,"total_supply":300000000.0,"max_supply":null,"ath":12.94,"ath_change_percentage":-59.91595,"ath_date":"2021-05-12T11:39:16.531Z","atl":0.25754,"atl_change_percentage":1914.2955,"atl_date":"2020-03-13T02:18:02.481Z","roi":null,"last_updated":"2023-12-16T00:46:03.220Z"},{"id":"tokenize-xchange","symbol":"tkx","name":"Tokenize Xchange","image":"https://assets.coingecko.com/coins/images/4984/large/TKX_-_Logo_-_RGB-15.png?1696505519","current_price":8.69,"market_cap":692782702,"market_cap_rank":89,"fully_diluted_valuation":866021679,"total_volume":14452607,"high_24h":9.0,"low_24h":8.62,"price_change_24h":0.071155,"price_change_percentage_24h":0.82569,"market_cap_change_24h":4837960,"market_cap_change_percentage_24h":0.70325,"circulating_supply":79995999.94518414,"total_supply":100000000.0,"max_supply":100000000.0,"ath":22.3,"ath_change_percentage":-61.21958,"ath_date":"2022-10-31T10:23:59.455Z","atl":0.111255,"atl_change_percentage":7671.87227,"atl_date":"2019-04-28T00:00:00.000Z","roi":{"times":28.90982896081179,"currency":"usd","percentage":2890.982896081179},"last_updated":"2023-12-16T00:45:40.887Z"},{"id":"cheelee","symbol":"cheel","name":"Cheelee","image":"https://assets.coingecko.com/coins/images/28573/large/CHEEL_%D1%82%D0%BE%D0%BD%D0%BA%D0%B0%D1%8F_%D0%BE%D0%B1%D0%B2%D0%BE%D0%B4%D0%BA%D0%B0_%283%29.png?1696527561","current_price":12.77,"market_cap":687659350,"market_cap_rank":90,"fully_diluted_valuation":12772557565,"total_volume":4955380,"high_24h":13.17,"low_24h":12.65,"price_change_24h":-0.32887599296834047,"price_change_percentage_24h":-2.50979,"market_cap_change_24h":-20012582.11353469,"market_cap_change_percentage_24h":-2.82795,"circulating_supply":53838813.8943758,"total_supply":1000000000.0,"max_supply":1000000000.0,"ath":17.32,"ath_change_percentage":-26.15957,"ath_date":"2023-07-16T21:40:08.888Z","atl":3.44,"atl_change_percentage":271.81274,"atl_date":"2023-02-13T02:53:08.933Z","roi":null,"last_updated":"2023-12-16T00:46:12.502Z"},{"id":"fetch-ai","symbol":"fet","name":"Fetch.ai","image":"https://assets.coingecko.com/coins/images/5681/large/Fetch.jpg?1696506140","current_price":0.649875,"market_cap":677839165,"market_cap_rank":91,"fully_diluted_valuation":748993553,"total_volume":288301889,"high_24h":0.746682,"low_24h":0.64983,"price_change_24h":-0.05125890732574312,"price_change_percentage_24h":-7.31086,"market_cap_change_24h":-49288960.1637336,"market_cap_change_percentage_24h":-6.77858,"circulating_supply":1043462805.0,"total_supply":1152997575.0,"max_supply":1152997575.0,"ath":1.17,"ath_change_percentage":-44.56891,"ath_date":"2021-09-08T02:24:24.858Z","atl":0.00816959,"atl_change_percentage":7852.04918,"atl_date":"2020-03-13T02:24:18.347Z","roi":{"times":6.495675824553258,"currency":"usd","percentage":649.5675824553258},"last_updated":"2023-12-16T00:46:02.724Z"},{"id":"frax-ether","symbol":"frxeth","name":"Frax Ether","image":"https://assets.coingecko.com/coins/images/28284/large/frxETH_icon.png?1696527284","current_price":2229.26,"market_cap":675017730,"market_cap_rank":92,"fully_diluted_valuation":675017730,"total_volume":2486394,"high_24h":2302.94,"low_24h":2223.01,"price_change_24h":-73.67215347870842,"price_change_percentage_24h":-3.19905,"market_cap_change_24h":-24487585.70955336,"market_cap_change_percentage_24h":-3.5007,"circulating_supply":302410.259870248,"total_supply":302410.259870248,"max_supply":null,"ath":2393.75,"ath_change_percentage":-6.99859,"ath_date":"2023-12-09T08:29:30.943Z","atl":1137.25,"atl_change_percentage":95.75495,"atl_date":"2022-11-23T02:25:33.267Z","roi":null,"last_updated":"2023-12-16T00:45:55.459Z"},{"id":"arweave","symbol":"ar","name":"Arweave","image":"https://assets.coingecko.com/coins/images/4343/large/oRt6SiEN_400x400.jpg?1696504946","current_price":9.98,"market_cap":649230177,"market_cap_rank":93,"fully_diluted_valuation":649230177,"total_volume":57052419,"high_24h":10.54,"low_24h":9.32,"price_change_24h":0.187748,"price_change_percentage_24h":1.91774,"market_cap_change_24h":21304669,"market_cap_change_percentage_24h":3.39287,"circulating_supply":65454185.5381511,"total_supply":65454185.5381511,"max_supply":66000000.0,"ath":89.24,"ath_change_percentage":-88.89383,"ath_date":"2021-11-05T04:14:42.689Z","atl":0.298788,"atl_change_percentage":3216.93789,"atl_date":"2020-01-31T06:47:36.543Z","roi":{"times":12.48351387747418,"currency":"usd","percentage":1248.3513877474181},"last_updated":"2023-12-16T00:46:05.983Z"},{"id":"frax","symbol":"frax","name":"Frax","image":"https://assets.coingecko.com/coins/images/13422/large/FRAX_icon.png?1696513182","current_price":0.99784,"market_cap":647421412,"market_cap_rank":94,"fully_diluted_valuation":647421412,"total_volume":6098509,"high_24h":1.001,"low_24h":0.99533,"price_change_24h":-0.000291067637243403,"price_change_percentage_24h":-0.02916,"market_cap_change_24h":639843,"market_cap_change_percentage_24h":0.09893,"circulating_supply":649462235.510511,"total_supply":649462235.510511,"max_supply":null,"ath":1.14,"ath_change_percentage":-12.34428,"ath_date":"2021-02-07T12:55:35.766Z","atl":0.874536,"atl_change_percentage":14.30866,"atl_date":"2023-03-11T07:50:39.316Z","roi":null,"last_updated":"2023-12-16T00:46:06.231Z"},{"id":"frax-share","symbol":"fxs","name":"Frax Share","image":"https://assets.coingecko.com/coins/images/13423/large/Frax_Shares_icon.png?1696513183","current_price":8.58,"market_cap":643839468,"market_cap_rank":95,"fully_diluted_valuation":849428014,"total_volume":31440046,"high_24h":9.19,"low_24h":8.53,"price_change_24h":-0.6092289445127133,"price_change_percentage_24h":-6.62756,"market_cap_change_24h":-48309621.90474236,"market_cap_change_percentage_24h":-6.97966,"circulating_supply":75555409.1576997,"total_supply":99681495.5911336,"max_supply":99681495.5911336,"ath":42.8,"ath_change_percentage":-80.01779,"ath_date":"2022-01-12T15:22:27.465Z","atl":1.5,"atl_change_percentage":468.9574,"atl_date":"2021-06-25T16:50:51.447Z","roi":null,"last_updated":"2023-12-16T00:45:51.610Z"},{"id":"ecash","symbol":"xec","name":"eCash","image":"https://assets.coingecko.com/coins/images/16646/large/Logo_final-22.png?1696516207","current_price":3.267e-05,"market_cap":637914978,"market_cap_rank":96,"fully_diluted_valuation":684190979,"total_volume":8862184,"high_24h":3.512e-05,"low_24h":3.26e-05,"price_change_24h":-2.330557957441e-06,"price_change_percentage_24h":-6.65911,"market_cap_change_24h":-30096696.175522685,"market_cap_change_percentage_24h":-4.50541,"circulating_supply":19579642173092.0,"total_supply":21000000000000.0,"max_supply":21000000000000.0,"ath":0.00038001,"ath_change_percentage":-91.41612,"ath_date":"2021-09-04T17:09:31.137Z","atl":1.847e-05,"atl_change_percentage":76.61085,"atl_date":"2021-07-20T20:49:46.212Z","roi":null,"last_updated":"2023-12-16T00:46:10.171Z"},{"id":"chiliz","symbol":"chz","name":"Chiliz","image":"https://assets.coingecko.com/coins/images/8834/large/CHZ_Token_updated.png?1696508986","current_price":0.081909,"market_cap":624330130,"market_cap_rank":97,"fully_diluted_valuation":724957267,"total_volume":79083211,"high_24h":0.086212,"low_24h":0.081595,"price_change_24h":-0.004302597836073869,"price_change_percentage_24h":-4.99071,"market_cap_change_24h":-35268637.50700688,"market_cap_change_percentage_24h":-5.34698,"circulating_supply":7655073480.0,"total_supply":8888888888.0,"max_supply":8888888888.0,"ath":0.878633,"ath_change_percentage":-90.71643,"ath_date":"2021-03-13T08:04:21.200Z","atl":0.00410887,"atl_change_percentage":1885.17989,"atl_date":"2019-09-28T00:00:00.000Z","roi":{"times":2.723158741234662,"currency":"usd","percentage":272.3158741234662},"last_updated":"2023-12-16T00:45:54.452Z"},{"id":"sui","symbol":"sui","name":"Sui","image":"https://assets.coingecko.com/coins/images/26375/large/sui_asset.jpeg?1696525453","current_price":0.602193,"market_cap":622574663,"market_cap_rank":98,"fully_diluted_valuation":6025329334,"total_volume":82151391,"high_24h":0.650172,"low_24h":0.601205,"price_change_24h":-0.0478479985863286,"price_change_percentage_24h":-7.36077,"market_cap_change_24h":-47706943.42918146,"market_cap_change_percentage_24h":-7.11745,"circulating_supply":1033262462.93308,"total_supply":10000000000.0,"max_supply":10000000000.0,"ath":2.16,"ath_change_percentage":-71.43964,"ath_date":"2023-05-03T12:00:26.430Z","atl":0.364846,"atl_change_percentage":69.28288,"atl_date":"2023-10-19T10:40:30.078Z","roi":null,"last_updated":"2023-12-16T00:46:11.401Z"},{"id":"conflux-token","symbol":"cfx","name":"Conflux","image":"https://assets.coingecko.com/coins/images/13079/large/3vuYMbjN.png?1696512867","current_price":0.174673,"market_cap":618803601,"market_cap_rank":99,"fully_diluted_valuation":949269544,"total_volume":72077815,"high_24h":0.199628,"low_24h":0.174211,"price_change_24h":-0.014926618777311636,"price_change_percentage_24h":-7.87269,"market_cap_change_24h":-54502700.439857006,"market_cap_change_percentage_24h":-8.09479,"circulating_supply":3552086158.36199,"total_supply":5449055651.90706,"max_supply":null,"ath":1.7,"ath_change_percentage":-89.74029,"ath_date":"2021-03-27T03:43:35.178Z","atl":0.02199898,"atl_change_percentage":693.22717,"atl_date":"2022-12-30T08:16:30.345Z","roi":null,"last_updated":"2023-12-16T00:46:07.887Z"},{"id":"kujira","symbol":"kuji","name":"Kujira","image":"https://assets.coingecko.com/coins/images/20685/large/kuji-200x200.png?1696520085","current_price":5.03,"market_cap":615481862,"market_cap_rank":100,"fully_diluted_valuation":615606860,"total_volume":3410175,"high_24h":5.32,"low_24h":5.03,"price_change_24h":-0.19158366978450125,"price_change_percentage_24h":-3.66704,"market_cap_change_24h":-30839523.155923843,"market_cap_change_percentage_24h":-4.77155,"circulating_supply":122349633.970196,"total_supply":122374481.990696,"max_supply":122398170.0,"ath":5.56,"ath_change_percentage":-9.47868,"ath_date":"2023-12-14T13:05:04.042Z","atl":0.00178701,"atl_change_percentage":281477.99284,"atl_date":"2022-05-20T01:46:32.095Z","roi":null,"last_updated":"2023-12-16T00:46:12.054Z"}]